graphs_edjedovi/__init__.py
graphs_edjedovi/heapq.py
graphs_edjedovi/sp.py
graphs_edjedovi-0.0.2.dist-info/METADATA
graphs_edjedovi-0.0.2.dist-info/WHEEL
graphs_edjedovi-0.0.2.dist-info/RECORD
